jwt_authenticator/__init__.py
jwt_authenticator/authentication_handler.py
jwt_authenticator/py.typed
jwt_authenticator-1.11.4.dist-info/METADATA
jwt_authenticator-1.11.4.dist-info/WHEEL
jwt_authenticator-1.11.4.dist-info/licenses/LICENSE
jwt_authenticator-1.11.4.dist-info/RECORD
