Metadata-Version: 2.4
Name: jwt-authenticator
Version: 1.11.4
Summary: Simple JWT token flask service security library.
Project-URL: Source, https://github.com/TeleTrackingTechnologies/jwt_authenticator
Author-email: Mike Nacey <nobody@teletracking.com>
License: The MIT License (MIT)
License-File: LICENSE
Keywords: authentication,flask,jwt
Classifier: Development Status :: 3 - Alpha
Classifier: License :: OSI Approved :: MIT License
Classifier: Operating System :: OS Independent
Classifier: Programming Language :: Python :: 3
Requires-Python: >=3.9
Requires-Dist: cryptography>=43.0.3
Requires-Dist: flask>=3.0.3
Requires-Dist: pyjwt>=2.9.0
